chameleon_log/__init__.py
chameleon_log/amend.py
chameleon_log/detectors.py
chameleon_log/py.typed
chameleon_log-0.2.0.dist-info/LICENSE
chameleon_log-0.2.0.dist-info/WHEEL
chameleon_log-0.2.0.dist-info/METADATA
chameleon_log-0.2.0.dist-info/RECORD
