Metadata-Version: 2.1
Name: chameleon-log
Version: 0.2.0
Summary: Python colored logging setup which adapts to environment
Home-page: https://github.com/AgriConnect/chameleon-log
License: MIT
Author: Nguyễn Hồng Quân
Author-email: ng.hong.quan@gmail.com
Requires-Python: >=3.6,<4.0
Classifier: Intended Audience :: Developers
Classifier: License :: OSI Approved :: MIT License
Classifier: Operating System :: POSIX :: Linux
Classifier: Programming Language :: Python :: 3
Classifier: Programming Language :: Python :: 3 :: Only
Classifier: Programming Language :: Python :: 3.10
Classifier: Programming Language :: Python :: 3.6
Classifier: Programming Language :: Python :: 3.7
Classifier: Programming Language :: Python :: 3.8
Classifier: Programming Language :: Python :: 3.9
Classifier: Topic :: Software Development :: Libraries :: Python Modules
Classifier: Topic :: System :: Logging
Requires-Dist: logbook (>=1.5.3,<2.0.0)
Requires-Dist: single-version (>=1.5.1,<2.0.0)
Project-URL: Repository, https://github.com/AgriConnect/chameleon-log.git
